{"job_id":908295274328823,"run_id":185456394896293,"creator_user_name":"la.long.n@outlook.com","number_in_job":185456394896293,"state":{"life_cycle_state":"INTERNAL_ERROR","result_state":"FAILED","state_message":"Task bronze_tmp failed with message: Workload failed, see run output for details.","user_cancelled_or_timedout":false},"start_time":1762883059281,"setup_duration":161000,"execution_duration":58000,"cleanup_duration":1000,"end_time":1762883279783,"run_duration":220502,"run_name":"superwind-polygon-bronze-tmp2","run_page_url":"https://dbc-51f1a5f2-687a.cloud.databricks.com/?o=683875129393773#job/908295274328823/run/185456394896293","run_type":"SUBMIT_RUN","tasks":[{"run_id":794184640677217,"task_key":"bronze_tmp","run_if":"ALL_SUCCESS","notebook_task":{"notebook_path":"/Users/datsando@outlook.com/superwind/notebooks/exec-superwind","base_parameters":{"yaml_file":"../pipelines/polygon/bronze.polygon.snapshot_all_tickers.tmp.yaml"},"source":"WORKSPACE"},"new_cluster":{"spark_version":"14.3.x-scala2.12","spark_conf":{"spark.master":"local[*, 4]","spark.databricks.cluster.profile":"singleNode","spark.databricks.delta.properties.defaults.autoOptimize.optimizeWrite":"true","spark.databricks.delta.properties.defaults.enableChangeDataFeed":"true"},"aws_attributes":{"first_on_demand":1,"availability":"SPOT_WITH_FALLBACK","zone_id":"auto","spot_bid_price_percent":100,"ebs_volume_count":0},"node_type_id":"r6id.2xlarge","driver_node_type_id":"r6id.2xlarge","custom_tags":{"ResourceClass":"SingleNode"},"spark_env_vars":{"PYSPARK_PYTHON":"/databricks/python3/bin/python3","DATSANDO_BUCKET_NAME":"datsando-prod"},"enable_elastic_disk":false,"policy_id":"0010BA4A1D3480A4","data_security_mode":"SINGLE_USER","runtime_engine":"STANDARD","num_workers":0},"libraries":[{"pypi":{"package":"pydantic==2.8.2"}},{"pypi":{"package":"pyyaml==6.0.2"}},{"pypi":{"package":"keyring==25.3.0"}}],"state":{"life_cycle_state":"TERMINATED","result_state":"FAILED","state_message":"Workload failed, see run output for details","user_cancelled_or_timedout":false},"run_page_url":"https://dbc-51f1a5f2-687a.cloud.databricks.com/?o=683875129393773#job/908295274328823/run/794184640677217","start_time":1762883059308,"setup_duration":161000,"execution_duration":58000,"cleanup_duration":1000,"end_time":1762883279520,"cluster_instance":{"cluster_id":"1111-174420-3v7kirdc","spark_context_id":"8039272567343212"},"attempt_number":0,"status":{"state":"TERMINATED","termination_details":{"code":"RUN_EXECUTION_ERROR","type":"CLIENT_ERROR","message":"Workload failed, see run output for details"}}}],"format":"MULTI_TASK","status":{"state":"TERMINATED","termination_details":{"code":"RUN_EXECUTION_ERROR","type":"CLIENT_ERROR","message":"Task bronze_tmp failed with message: Workload failed, see run output for details."}},"job_run_id":185456394896293}